{"titulo":"Sistema de Gerenciamento de Frota Online","postits":[{"cor":1,"texto":"Empresas do agronegócio que possuam frotas de veículos e motoristas.","where":0},{"cor":0,"texto":"Empresas de revenda de autopeças.","where":0},{"cor":0,"texto":"Agencias de emprego que contratem motoristas.","where":0},{"cor":2,"texto":"AWS, Azure, Google e outras empresas de tecnologia.","where":0},{"cor":1,"texto":"Desenvolver o sistema Fullstack.","where":1},{"cor":0,"texto":"Realizar testes, unitários, integração e ponto a ponto.","where":1},{"cor":1,"texto":"Desenvolvedores de sistema","where":2},{"cor":0,"texto":"Laboratório de informática com computadores em ambiente DEV.","where":2},{"cor":1,"texto":"Tempo de desenvolvimento, Programador júnior R$ 18,00 a hora (03/2023)","where":7},{"cor":0,"texto":"Energia elétrica. R$ 0,01 hora / Dev","where":7},{"cor":2,"texto":"Consultoria com 2 instrutores do SENAI.","where":7},{"cor":0,"texto":"Aprimorar o controle veicular.","where":3},{"cor":1,"texto":"Auxiliar na tomada de decisões de negócio","where":3},{"cor":0,"texto":"Geração de relatórios claros e precisos","where":3},{"cor":0,"texto":"Realizar as entregas dentro do prazo.","where":4},{"cor":1,"texto":"Solucionar o problema","where":4},{"cor":2,"texto":"Propaganda boca a boca. Após o primeiro cliente satisfeito, divulgar para outros interessados","where":5},{"cor":1,"texto":"Empreendedores rurais que possuam frotas de veículos","where":6},{"cor":0,"texto":"Qualquer empresa que possua frota de veículos e motoristas contratados","where":6},{"cor":0,"texto":"R$ 18,00 x 110 horas = R$ 1980,00","where":8}]}